alphagradient/__init__.py
alphagradient/_algorithm.py
alphagradient/_globals.py
alphagradient/_proxy.py
alphagradient/dtypes.py
alphagradient/utils.py
alphagradient/_data/__init__.py
alphagradient/_data/_datatools.py
alphagradient/_finance/__init__.py
alphagradient/_finance/_asset.py
alphagradient/_finance/_collections.py
alphagradient/_finance/_portfolio.py
alphagradient/_finance/_standard.py
alphagradient/_finance/currency_info.p
alphagradient/_finance/exchange_info.p
alphagradient/_finance/standard_asset_settings.yml
alphagradient/_models/__init__.py
alphagradient/_models/templates.py
alphagradient/_models/train.py
alphagradient/_models/trained/__init__.py
alphagradient/_models/trained/trained_models.py
alphagradient/algolib/__init__.py
alphagradient/algolib/_lib.py
alphagradient-0.0.2.2.dist-info/LICENSE
alphagradient-0.0.2.2.dist-info/METADATA
alphagradient-0.0.2.2.dist-info/WHEEL
alphagradient-0.0.2.2.dist-info/top_level.txt
alphagradient-0.0.2.2.dist-info/RECORD
