Metadata-Version: 2.1
Name: alphagradient
Version: 0.0.2.2
Summary: A tool for creating and backtesting financial algorithms
Home-page: https://github.com/nathanheidacker/alphagradient
Author: Nathan Heidacker
Author-email: nathanheidacker2022@u.northwestern.edu
License: Apache License
Project-URL: Documentation, https://github.com/nathanheidacker/alphagradient
Project-URL: Source Code, https://github.com/nathanheidacker/alphagradient
Platform: unix
Platform: linux
Platform: osx
Platform: win32
Classifier: Development Status :: 2 - Pre-Alpha
Classifier: Intended Audience :: Developers
Classifier: Intended Audience :: Education
Classifier: Intended Audience :: End Users/Desktop
Classifier: Intended Audience :: Financial and Insurance Industry
Classifier: Intended Audience :: Information Technology
Classifier: Intended Audience :: Science/Research
Classifier: License :: OSI Approved :: Apache Software License
Classifier: Programming Language :: Python :: 3
Classifier: Programming Language :: Python :: 3 :: Only
Classifier: Programming Language :: Python :: 3.8
Classifier: Programming Language :: Python :: 3.9
Requires-Python: >=3.8
License-File: LICENSE
Requires-Dist: p-tqdm (>=1)
Requires-Dist: tqdm (>=4)
Requires-Dist: bs4
Requires-Dist: numpy (>=1)
Requires-Dist: pandas (>=1)
Requires-Dist: yfinance (>=0.1)
Requires-Dist: aenum (>=3)
Requires-Dist: pyyaml
Requires-Dist: typing-extensions
Provides-Extra: testing
Requires-Dist: pytest (>=6.0) ; extra == 'testing'
Requires-Dist: pytest-cov (>=2.0) ; extra == 'testing'
Requires-Dist: flake8 (>=3.9) ; extra == 'testing'
Requires-Dist: tox (>=3.24) ; extra == 'testing'
